{"frames": {

"eggBlueLight_016.png":
{
	"frame": {"x":844,"y":844,"w":831,"h":832},
	"rotated": true,
	"trimmed": false,
	"spriteSourceSize": {"x":545,"y":110,"w":831,"h":832},
	"sourceSize": {"w":831,"h":832},
	"anchor": {"x":0.499398,"y":0.588942}
},
"eggOrangeLight_017.png":
{
	"frame": {"x":1,"y":1,"w":841,"h":841},
	"rotated": false,
	"trimmed": false,
	"spriteSourceSize": {"x":540,"y":105,"w":841,"h":841},
	"sourceSize": {"w":841,"h":841},
	"anchor": {"x":0.499405,"y":0.588585}
},
"eggPurpleLight_005.png":
{
	"frame": {"x":844,"y":1677,"w":355,"h":355},
	"rotated": false,
	"trimmed": false,
	"spriteSourceSize": {"x":792,"y":391,"w":355,"h":355},
	"sourceSize": {"w":355,"h":355},
	"anchor": {"x":0.473239,"y":0.588732}
},
"eggPurpleLight_017.png":
{
	"frame": {"x":844,"y":1,"w":841,"h":841},
	"rotated": false,
	"trimmed": false,
	"spriteSourceSize": {"x":540,"y":105,"w":841,"h":841},
	"sourceSize": {"w":841,"h":841},
	"anchor": {"x":0.499405,"y":0.588585}
},
"eggWhtie light_005.png":
{
	"frame": {"x":1201,"y":1677,"w":355,"h":355},
	"rotated": false,
	"trimmed": false,
	"spriteSourceSize": {"x":792,"y":391,"w":355,"h":355},
	"sourceSize": {"w":355,"h":355},
	"anchor": {"x":0.473239,"y":0.588732}
},
"eggWhtie light_017.png":
{
	"frame": {"x":1,"y":844,"w":841,"h":841},
	"rotated": false,
	"trimmed": false,
	"spriteSourceSize": {"x":540,"y":105,"w":841,"h":841},
	"sourceSize": {"w":841,"h":841},
	"anchor": {"x":0.499405,"y":0.588585}
}},
"animations": {
	"eggPurpleLight": ["eggPurpleLight_005.png","eggPurpleLight_017.png"],
	"eggWhtie light": ["eggWhtie light_005.png","eggWhtie light_017.png"]
},
"meta": {
	"app": "https://www.codeandweb.com/texturepacker",
	"version": "1.0",
	"image": "blueLight-8.png",
	"format": "RGBA8888",
	"size": {"w":1686,"h":2033},
	"scale": "1",
	"related_multi_packs": [ "blueLight-0.json", "blueLight-1.json", "blueLight-2.json", "blueLight-3.json", "blueLight-4.json", "blueLight-5.json", "blueLight-6.json", "blueLight-7.json", "blueLight-9.json", "blueLight-10.json", "blueLight-11.json", "blueLight-12.json", "blueLight-13.json", "blueLight-14.json", "blueLight-15.json", "blueLight-16.json", "blueLight-17.json" ],
	"smartupdate": "$TexturePacker:SmartUpdate:7cf533701c14b9c4c6a6f33e7feac816:87adf437a90981cb599004c0d5c3605a:03e57e94f60810a34fd380df8995d866$"
}
}
